<?xml version="1.0" encoding="utf-8" ?>
<dwsync>
<file name="TopBack.png" local="127682935200000000" remote="128382141600000000" testing="0" />
<file name="TopPic1.png" local="127682937300000000" remote="128382141600000000" testing="0" />
<file name="TopPic2.png" local="127682937340000000" remote="128382141000000000" testing="0" />
<file name="SideTopDefault.png" local="127683023640000000" remote="128382141000000000" testing="0" />
<file name="SideBack.png" local="127682962440000000" remote="128382141000000000" testing="0" />
<file name="SideBottom.png" local="127682981440000000" remote="128382141000000000" testing="0" />
<file name="logIcon.gif" local="127682989380000000" remote="128382141000000000" testing="0" />
<file name="Message.jpg" local="127683027000000000" remote="128382141000000000" testing="0" />
<file name="Error.jpg" local="127683026240000000" remote="128382141000000000" testing="0" />
<file name="Warning.jpg" local="127683026260000000" remote="128382141000000000" testing="0" />
<file name="arrow.gif" local="127682972640000000" remote="128382141000000000" testing="0" />
<file name="bullet-arrow.gif" local="127656283620000000" remote="128382141000000000" testing="0" />
<file name="bb.gif" local="127682983340000000" remote="128382141600000000" testing="0" />
<file name="Cprevious.gif" local="127676800420000000" remote="128382141600000000" testing="0" />
<file name="Cnext.gif" local="127676800080000000" remote="128382141600000000" testing="0" />
<file name="global.css" local="127700370240000000" remote="128382141000000000" testing="0" />
<file name="layout.css" local="127703170240000000" remote="128382141000000000" testing="0" />
<file name="link.css" local="127700370060000000" remote="128382141000000000" testing="0" />
<file name="mback.png" local="127645268620000000" remote="128382141000000000" testing="0" />
<file name="MN.gif" local="127683013560000000" remote="128382141000000000" testing="0" />
<file name="MP.gif" local="127683014260000000" remote="128382141000000000" testing="0" />
<file name="Question.jpg" local="127683026980000000" remote="128382141000000000" testing="0" />
<file name="SideBackC.png" local="127683030020000000" remote="128382141600000000" testing="0" />
<file name="skin.xml" local="128371607992968750" remote="128382141600000000" testing="0" />
<file name="typography.css" local="127683028540000000" remote="128382141600000000" testing="0" />
</dwsync>